dropbox_api_team_4/__init__.py
dropbox_api_team_4/dropbox_logic.py
dropbox_api_team_4/func/__init__.py
dropbox_api_team_4/func/check_api_token.py
dropbox_api_team_4/func/download_file.py
dropbox_api_team_4/func/error_processing.py
dropbox_api_team_4-0.2.1.dist-info/entry_points.txt
dropbox_api_team_4-0.2.1.dist-info/WHEEL
dropbox_api_team_4-0.2.1.dist-info/METADATA
dropbox_api_team_4-0.2.1.dist-info/RECORD
